{
  "AADI": "PT Adaro Andalan Indonesia Tbk",
  "AALI": "PT Astra Agro Lestari Tbk",
  "ABMM": "PT ABM Investama Tbk",
  "ACES": "PT Aspirasi Hidup Indonesia Tbk",
  "ACRO": "PT Samcro Hyosung Adilestari Tbk",
  "ADMF": "PT Adira Dinamika Multi Finance Tbk",
  "ADMR": "PT Adaro Minerals Indonesia Tbk",
  "ADRO": "PT Adaro Energy Indonesia Tbk",
  "AGII": "PT Samator Indo Gas Tbk",
  "AKPI": "PT Argha Karya Prima Industri Tbk",
  "AKRA": "PT AKR Corporindo Tbk",
  "ALDO": "PT Alkindo Naratama Tbk",
  "ALII": "PT Anugerah Spareparts Sejahtera Tbk",
  "AMAG": "PT Asuransi Multi Artha Guna Tbk",
  "AMAR": "PT Bank Amar Indonesia Tbk",
  "AMFG": "PT Asahimas Flat Glass Tbk",
  "AMIN": "PT Atamina Kencana Tbk",
  "AMOR": "PT Ashmore Asset Management Indonesia Tbk",
  "AMRT": "PT Sumber Alfaria Trijaya Tbk",
  "ANTM": "PT Aneka Tambang Tbk",
  "ARCI": "PT Archi Indonesia Tbk",
  "ARNA": "PT Arwana Citramulia Tbk",
  "ARTA": "PT Arthavest Tbk",
  "ASBI": "PT Asuransi Bintang Tbk",
  "ASDM": "PT Asuransi Dayin Mitra Tbk",
  "ASGR": "PT Astra Graphia Tbk",
  "ASII": "PT Astra International Tbk",
  "ASJT": "PT Asuransi Jasa Tania Tbk",
  "ASLC": "PT Autopedia Sukses Lestari Tbk",
  "ASRM": "PT Asuransi Ramayana Tbk",
  "ASSA": "PT Adi Sarana Armada Tbk",
  "ATLA": "PT Atlantis Subsea Indonesia Tbk",
  "AUTO": "PT Astra Otoparts Tbk",
  "AVIA": "PT Avia Avian Tbk",
  "AXIO": "PT Tera Data Indonusa Tbk",
  "BALI": "PT Bali Towerindo Sentra Tbk",
  "BATR": "PT Barito Renewables Energy Tbk",
  "BAYU": "PT Bayu Buana Tbk",
  "BBCA": "PT Bank Central Asia Tbk",
  "BBHI": "PT Allo Bank Indonesia Tbk",
  "BBLD": "PT Buana Finance Tbk",
  "BBMD": "PT Bank Mestika Dharma Tbk",
  "BBNI": "PT Bank Negara Indonesia (Persero) Tbk",
  "BBRI": "PT Bank Rakyat Indonesia (Persero) Tbk",
  "BBTN": "PT Bank Tabungan Negara (Persero) Tbk",
  "BDKR": "PT Berdikari Pondasi Perkasa Tbk",
  "BDMN": "PT Bank Danamon Indonesia Tbk",
  "BELL": "PT Trisula Textile Industries Tbk",
  "BFIN": "PT BFI Finance Indonesia Tbk",
  "BIKE": "PT Sepeda Bersama Indonesia Tbk",
  "BIRD": "PT Blue Bird Tbk",
  "BISI": "PT BISI International Tbk",
  "BJBR": "PT Bank Pembangunan Daerah Jawa Barat dan Banten Tbk",
  "BJTM": "PT Bank Pembangunan Daerah Jawa Timur Tbk",
  "BLES": "PT Superior Prima Sukses Tbk",
  "BLUE": "PT Berkah Prima Perkasa Tbk",
  "BMHS": "PT Bundamedik Tbk",
  "BMRI": "PT Bank Mandiri (Persero) Tbk",
  "BNGA": "PT Bank CIMB Niaga Tbk",
  "BNII": "PT Bank Maybank Indonesia Tbk",
  "BNLI": "PT Bank Permata Tbk",
  "BOBA": "PT Formosa Ingredient Factory Tbk",
  "BOLT": "PT Garuda Metalindo Tbk",
  "BPFI": "PT Batavia Prosperindo Finance Tbk",
  "BPII": "PT Batavia Prosperindo Internasional Tbk",
  "BRIS": "PT Bank Syariah Indonesia Tbk",
  "BSSR": "PT Baramulti Suksessarana Tbk",
  "BTPN": "PT Bank BTPN Tbk",
  "BTPS": "PT Bank BTPN Syariah Tbk",
  "BUAH": "PT Segar Kumala Indonesia Tbk",
  "BUDI": "PT Budi Starch & Sweetener Tbk",
  "BYAN": "PT Bayan Resources Tbk",
  "CBDK": "PT Bangun Kosambi Sukses Tbk",
  "CBPE": "PT Citra Nusantara Gemilang Tbk",
  "CDIA": "PT Cinere Delta Indonesia Tbk",
  "CEKA": "PT Wilmar Cahaya Indonesia Tbk",
  "CFIN": "PT Clipan Finance Indonesia Tbk",
  "CGAS": "PT Citra Nusantara Gemilang Tbk",
  "CHEM": "PT Chemstar Indonesia Tbk",
  "CHIP": "PT Pelita Teknologi Global Tbk",
  "CINT": "PT Chitose Internasional Tbk",
  "CITA": "PT Cita Mineral Investindo Tbk",
  "CLEO": "PT Sariguna Primatirta Tbk",
  "CLPI": "PT Colorpak Indonesia Tbk",
  "CMRY": "PT Cisarua Mountain Dairy Tbk",
  "CNMA": "PT Nusantara Sejahtera Raya Tbk",
  "CPIN": "PT Charoen Pokphand Indonesia Tbk",
  "CRAB": "PT Toba Surimi Lestari Tbk",
  "CRSN": "PT Carsurin Tbk",
  "CSAP": "PT Catur Sentosa Adipradana Tbk",
  "CSRA": "PT Cisadane Sawit Raya Tbk",
  "CTBN": "PT Citra Tubindo Tbk",
  "CTRA": "PT Ciputra Development Tbk",
  "CUAN": "PT Petrindo Jaya Kreasi Tbk",
  "DAAZ": "PT Daaz Bara Lestari Tbk",
  "DADA": "PT Diamond Citra Propertindo Tbk",
  "DEPO": "PT Caturkarda Depo Bangunan Tbk",
  "DGWG": "PT Dunia Virtual Online Tbk",
  "DKFT": "PT Central Omega Resources Tbk",
  "DLTA": "PT Delta Djakarta Tbk",
  "DMAS": "PT Puradelta Lestari Tbk",
  "DMND": "PT Diamond Food Indonesia Tbk",
  "DNET": "PT Indoritel Makmur Internasional Tbk",
  "DOSS": "PT Global Sukses Digital Tbk",
  "DPNS": "PT Duta Pertiwi Nusantara Tbk",
  "DRMA": "PT Dharma Polimetal Tbk",
  "DSNG": "PT Dharma Satya Nusantara Tbk",
  "DVLA": "PT Darya-Varia Laboratoria Tbk",
  "DWGL": "PT Dwi Guna Laksana Tbk",
  "EAST": "PT Eastparc Hotel Tbk",
  "EKAD": "PT Ekadharma International Tbk",
  "ELIT": "PT Data Sinergitama Indonesia Tbk",
  "ELPI": "PT Pelayaran Nasional Ekalya Purnamasari Tbk",
  "ELSA": "PT Elnusa Tbk",
  "EMTK": "PT Elang Mahkota Teknologi Tbk",
  "EPMT": "PT Enseval Putera Megatrading Tbk",
  "ERAA": "PT Erajaya Swasembada Tbk",
  "ERAL": "PT Sinar Eka Selaras Tbk",
  "ESIP": "PT Sinergi Inti Plastindo Tbk",
  "ESSA": "PT ESSA Indonesia Tbk",
  "EURO": "PT Euroisiatama Tbk",
  "EXCL": "PT XL Axiata Tbk",
  "FISH": "PT Fisha Media Indonesia Tbk",
  "FWCT": "PT Wijaya Cahaya Timber Tbk",
  "GDST": "PT Gunawan Dianjaya Steel Tbk",
  "GEMA": "PT Gema Grahasarana Tbk",
  "GEMS": "PT Golden Energy Mines Tbk",
  "GGRM": "PT Gudang Garam Tbk",
  "GGRP": "PT Gunung Raja Paksi Tbk",
  "GHON": "PT Gglobal Teleshop Tbk",
  "GJTL": "PT Gajah Tunggal Tbk",
  "GLVA": "PT Galva Technologies Tbk",
  "GMTD": "PT Gowa Makassar Tourism Development Tbk",
  "GOLF": "PT Intra Golflink Resorts Tbk",
  "GOOD": "PT Garudafood Putra Putri Jaya Tbk",
  "GPRA": "PT Perdana Gapuraprima Tbk",
  "GRPM": "PT GRPM Indonesia Tbk",
  "GTRA": "PT Grahatekindo Tbk",
  "GTSI": "PT GTS Internasional Tbk",
  "GUNA": "PT Guna Timur Raya Tbk",
  "HAIS": "PT Hasnur Internasional Shipping Tbk",
  "HEAL": "PT Medikaloka Hermina Tbk",
  "HEXA": "PT Hexindo Adiperkasa Tbk",
  "HGII": "PT Hartadinata Abadi Tbk",
  "HMSP": "PT H.M. Sampoerna Tbk",
  "HOKI": "PT Buyung Poetra Sembada Tbk",
  "HRTA": "PT Hartadinata Abadi Tbk",
  "HUMI": "PT Humpuss Maritim Internasional Tbk",
  "HYGN": "PT Ecocare Indo Pasifik Tbk",
  "ICBP": "PT Indofood CBP Sukses Makmur Tbk",
  "IDEA": "PT Idea Indonesia Akademi Tbk",
  "IDPR": "PT Indonesia Kendaraan Terminal Tbk",
  "IFII": "PT Indonesia Fibreboard Industry Tbk",
  "IFSH": "PT Ifishdeco Tbk",
  "IGAR": "PT Champion Pacific Indonesia Tbk",
  "IKBI": "PT Ikapharmindo Putramas Tbk",
  "IMAS": "PT Indomobil Sukses Internasional Tbk",
  "IMJS": "PT Indomobil Multi Jasa Tbk",
  "INCI": "PT Intanwijaya Internasional Tbk",
  "INCO": "PT Vale Indonesia Tbk",
  "INDF": "PT Indofood Sukses Makmur Tbk",
  "INDS": "PT Indospring Tbk",
  "INDY": "PT Indika Energy Tbk",
  "INET": "PT Sinergi Teknologi Digital Tbk",
  "INKP": "PT Indah Kiat Pulp & Paper Tbk",
  "INPP": "PT Indonesian Paradise Property Tbk",
  "INTP": "PT Indocement Tunggal Prakarsa Tbk",
  "IPCC": "PT Indonesia Kendaraan Terminal Tbk",
  "IPCM": "PT Jasa Armada Indonesia Tbk",
  "IRSX": "PT Aviana Sinar Abadi Tbk",
  "ISAT": "PT Indosat Tbk",
  "ISSP": "PT Steel Pipe Industry of Indonesia Tbk",
  "ITMG": "PT Indo Tambangraya Megah Tbk",
  "JARR": "PT Jhonlin Agro Raya Tbk",
  "JASS": "PT PT Jasa Angkasa Semesta Tbk",
  "JATI": "PT Informasi Teknologi Indonesia Tbk",
  "JAYA": "PT Armada Berjaya Trans Tbk",
  "JECC": "PT Jakarta Kyoei Steel Works Tbk",
  "JKON": "PT Jaya Konstruksi Manggala Pratama Tbk",
  "JPFA": "PT Japfa Comfeed Indonesia Tbk",
  "JRPT": "PT Jaya Real Property Tbk",
  "JSMR": "PT Jasa Marga (Persero) Tbk",
  "JSPT": "PT Jakarta Setiabudi Internasional Tbk",
  "JTPE": "PT Jasa Teknika Pengamanan Ekstra Tbk",
  "KBLI": "PT KMI Wire & Cable Tbk",
  "KBLM": "PT Kabelindo Murni Tbk",
  "KDSI": "PT Kedawung Setia Industrial Tbk",
  "KDTN": "PT Puri Sentul Permai Tbk",
  "KEEN": "PT Kencana Energi Lestari Tbk",
  "KEJU": "PT Mulia Boga Raya Tbk",
  "KIJA": "PT Kawasan Industri Jababeka Tbk",
  "KINO": "PT Kino Indonesia Tbk",
  "KKGI": "PT Resource Alam Indonesia Tbk",
  "KLAS": "PT Pelayaran Nasional Klasikal Tbk",
  "KLBF": "PT Kalbe Farma Tbk",
  "KMDS": "PT Kurniamitra Duta Sentosa Tbk",
  "KOCI": "PT Kokoh Inti Arebama Tbk",
  "KUAS": "PT Ace Oldfields Tbk",
  "LAJU": "PT Jasa Berdikari Nusantara Tbk",
  "LFLO": "PT Imago Mulia Persada Tbk",
  "LIFE": "PT Asuransi Jiwa Sinarmas MSIG Tbk",
  "LION": "PT Lion Metal Works Tbk",
  "LPGI": "PT Asuransi Lippo Tbk",
  "LPIN": "PT Multi Prima Sejahtera Tbk",
  "LPPF": "PT Matahari Department Store Tbk",
  "LSIP": "PT PP London Sumatra Indonesia Tbk",
  "LTLS": "PT Lautan Luas Tbk",
  "MAHA": "PT Mandiri Herindo Adiperkasa Tbk",
  "MAIN": "PT Malindo Feedmill Tbk",
  "MAPA": "PT Map Aktif Adiperkasa Tbk",
  "MAPI": "PT Mitra Adiperkasa Tbk",
  "MARK": "PT Mark Dynamics Indonesia Tbk",
  "MASA": "PT Multistrada Arah Sarana Tbk",
  "MASB": "PT Bank Multiarta Sentosa Tbk",
  "MBAP": "PT Mitrabara Adiperdana Tbk",
  "MCOL": "PT Prima Andalan Mandiri Tbk",
  "MDKI": "PT Emdeki Utama Tbk",
  "MDLA": "PT Citra Marga Nusaphala Persada Tbk",
  "MEDC": "PT Medco Energi Internasional Tbk",
  "MEGA": "PT Bank Mega Tbk",
  "MERK": "PT Merck Tbk",
  "META": "PT Nusantara Infrastructure Tbk",
  "MFIN": "PT Mandala Multifinance Tbk",
  "MFMI": "PT Multifiling Mitra Indonesia Tbk",
  "MHKI": "PT Multi Medika Internasional Tbk",
  "MICE": "PT Multi Indocitra Tbk",
  "MIDI": "PT Midi Utama Indonesia Tbk",
  "MIKA": "PT Mitra Keluarga Karyasehat Tbk",
  "MINE": "PT Mineral Sumberdaya Mandiri Tbk",
  "MKAP": "PT Multikarya Asia Pasifik Raya Tbk",
  "MKPI": "PT Metropolitan Kentjana Tbk",
  "MKTR": "PT Menthobi Karyatama Raya Tbk",
  "MLBI": "PT Multi Bintang Indonesia Tbk",
  "MLIA": "PT Mulia Industrindo Tbk",
  "MLPT": "PT Multipolar Technology Tbk",
  "MMLP": "PT Mega Manunggal Property Tbk",
  "MPIX": "PT Mitra Pedagang Indonesia Tbk",
  "MPMX": "PT Mitra Pinasthika Mustika Tbk",
  "MPXL": "PT MPX Logistics International Tbk",
  "MREI": "PT Maskapai Reasuransi Indonesia Tbk",
  "MSJA": "PT Majapahit Inti Corporindo Tbk",
  "MSTI": "PT Mandiri Digital Medika Tbk",
  "MTDL": "PT Metrodata Electronics Tbk",
  "MTEL": "PT Dayamitra Telekomunikasi Tbk",
  "MTLA": "PT Metropolitan Land Tbk",
  "MTWI": "PT Malacca Trust Wuwungan Insurance Tbk",
  "MUTU": "PT Mutuagung Lestari Tbk",
  "MYOH": "PT Samudra Indonesia Tbk",
  "MYOR": "PT Mayora Indah Tbk",
  "NAIK": "PT PT Master Kidz Indonesia Tbk",
  "NCKL": "PT Trimegah Bangun Persada Tbk",
  "NELY": "PT Pelayaran Nasional Nelly Dwi Putri Tbk",
  "NICL": "PT Mineral Global Indonesia Tbk",
  "NIKL": "PT Latinusa Tbk",
  "NISP": "PT Bank OCBC NISP Tbk",
  "NPGF": "PT Nusantara Pelabuhan Handal Tbk",
  "NRCA": "PT Nusa Raya Cipta Tbk",
  "NSSS": "PT Nusantara Sawit Sejahtera Tbk",
  "NTBK": "PT Bank NTB Syariah Tbk",
  "OBAT": "PT Formosa Ingredient Factory Tbk",
  "OMED": "PT Jayamas Medica Industri Tbk",
  "PANI": "PT Pantai Indah Kapuk Dua Tbk",
  "PANR": "PT Panorama Sentrawisata Tbk",
  "PANS": "PT Panin Sekuritas Tbk",
  "PART": "PT PT Auto Tri Utama Tbk",
  "PBID": "PT Panca Budi Idaman Tbk",
  "PBSA": "PT Paramita Bangun Sarana Tbk",
  "PDES": "PT Destinasi Tirta Nusantara Tbk",
  "PDPP": "PT PT Prima Radio Autoland Tbk",
  "PGAS": "PT Perusahaan Gas Negara Tbk",
  "PGEO": "PT Pertamina Geothermal Energy Tbk",
  "PGUN": "PT Permata Prima Indonesia Tbk",
  "PJAA": "PT Pembangunan Jaya Ancol Tbk",
  "PLIN": "PT Plaza Indonesia Realty Tbk",
  "PMJS": "PT PMJS Indonesia Tbk",
  "PMUI": "PT PT Paramita Media Utama Tbk",
  "PNBN": "PT Bank Pan Indonesia Tbk",
  "PNGO": "PT Pinago Utama Tbk",
  "PNSE": "PT Pudjiadi & Sons Tbk",
  "POWR": "PT Cikarang Listrindo Tbk",
  "PPGL": "PT Prima Globalindo Logistik Tbk",
  "PPRI": "PT PT Prima Perkasa Indonesia Tbk",
  "PRDA": "PT Prodia Widyahusada Tbk",
  "PSGO": "PT Palma Serasih Tbk",
  "PSSI": "PT Pelayaran Tamarin Samudra Tbk",
  "PTBA": "PT Bukit Asam Tbk",
  "PTPS": "PT Pulau Subur Tbk",
  "PTPW": "PT Pratama Widya Tbk",
  "PTRO": "PT Petrosea Tbk",
  "PTSN": "PT Sat Nusapersada Tbk",
  "PTSP": "PT Pioneerindo Gourmet International Tbk",
  "PWON": "PT Pakuwon Jati Tbk",
  "PZZA": "PT Sarimelati Kencana Tbk",
  "RAJA": "PT Rukun Raharja Tbk",
  "RALS": "PT Ramayana Lestari Sentosa Tbk",
  "RATU": "PT Ratu Prabu Tbk",
  "RDTX": "PT Roda Vivatex Tbk",
  "REAL": "PT PT Realindo Property Tbk",
  "RELF": "PT Graha Mitra Asia Tbk",
  "RGAS": "PT PT Rukun Raharja Gas Tbk",
  "RMKE": "PT RMK Energy Tbk",
  "ROTI": "PT Nippon Indosari Corpindo Tbk",
  "SAMF": "PT Saraswanti Anugerah Makmur Tbk",
  "SBMA": "PT Surya Biru Murni Acetylene Tbk",
  "SCCO": "PT Supreme Cable Manufacturing & Commerce Tbk",
  "SCMA": "PT Surya Citra Media Tbk",
  "SCNP": "PT Selaras Citra Nusantara Perkasa Tbk",
  "SDPC": "PT Millennium Pharmacon International Tbk",
  "SDRA": "PT Bank Woori Saudara Indonesia 1906 Tbk",
  "SGER": "PT Sumber Global Energy Tbk",
  "SGRO": "PT Sampoerna Agro Tbk",
  "SHIP": "PT Sillo Maritime Perdana Tbk",
  "SICO": "PT Sigma Energy Compressco Tbk",
  "SIDO": "PT Industri Jamu dan Farmasi Sido Muncul Tbk",
  "SIMP": "PT Salim Ivomas Pratama Tbk",
  "SKLT": "PT Sekar Laut Tbk",
  "SKRN": "PT Superkrane Mitra Utama Tbk",
  "SMAR": "PT Sinar Mas Agro Resources and Technology Tbk",
  "SMBR": "PT Semen Baturaja (Persero) Tbk",
  "SMCB": "PT Solusi Bangun Indonesia Tbk",
  "SMDR": "PT Samudera Indonesia Tbk",
  "SMGR": "PT Semen Indonesia (Persero) Tbk",
  "SMIL": "PT Sarana Mitra Luas Tbk",
  "SMKL": "PT Sinar Multi Laras Tbk",
  "SMRA": "PT Summarecon Agung Tbk",
  "SMSM": "PT Selamat Sempurna Tbk",
  "SOCI": "PT Soechi Lines Tbk",
  "SOHO": "PT Soho Global Health Tbk",
  "SOLA": "PT PT Solusi Logistik Asia Tbk",
  "SOSS": "PT Shield On Service Tbk",
  "SPTO": "PT Surya Pertiwi Tbk",
  "SRSN": "PT Indo Acidatama Tbk",
  "SRTG": "PT Saratoga Investama Sedaya Tbk",
  "SSIA": "PT Surya Semesta Internusa Tbk",
  "SSMS": "PT Sawit Sumbermas Sarana Tbk",
  "STAA": "PT Sumber Tani Agung Resources Tbk",
  "SUNI": "PT Sunindo Pratama Tbk",
  "SWID": "PT Saraswanti Indoland Pengembangan Tbk",
  "TALF": "PT Tunas Alfin Tbk",
  "TAPG": "PT Triputra Agro Persada Tbk",
  "TBIG": "PT Tower Bersama Infrastructure Tbk",
  "TBLA": "PT Tunas Baru Lampung Tbk",
  "TBMS": "PT Tembaga Mulia Semanan Tbk",
  "TCID": "PT Mandom Indonesia Tbk",
  "TCPI": "PT Transcoal Pacific Tbk",
  "TEBE": "PT Dana Brata Luhur Tbk",
  "TGKA": "PT Tigaraksa Satria Tbk",
  "TIFA": "PT KDB Tifa Finance Tbk",
  "TINS": "PT Timah Tbk",
  "TKIM": "PT Pabrik Kertas Tjiwi Kimia Tbk",
  "TLDN": "PT Teladan Prima Agro Tbk",
  "TLKM": "PT Telkom Indonesia (Persero) Tbk",
  "TMAS": "PT Temas Tbk",
  "TOBA": "PT TBS Energi Utama Tbk",
  "TOOL": "PT Tools Indonesia Tbk",
  "TOSK": "PT PT Toska Indonesia Tbk",
  "TOTL": "PT Total Bangun Persada Tbk",
  "TOTO": "PT Surya Toto Indonesia Tbk",
  "TOWR": "PT Sarana Menara Nusantara Tbk",
  "TPIA": "PT Chandra Asri Pacific Tbk",
  "TPMA": "PT Trans Power Marine Tbk",
  "TRIS": "PT Trisula International Tbk",
  "TRST": "PT Trias Sentosa Tbk",
  "TRUS": "PT Trust Finance Indonesia Tbk",
  "TSPC": "PT Tempo Scan Pacific Tbk",
  "TUGU": "PT Asuransi Tugu Pratama Indonesia Tbk",
  "UCID": "PT Uni-Charm Indonesia Tbk",
  "ULTJ": "PT Ultra Jaya Milk Industry & Trading Company Tbk",
  "UNIC": "PT Trans Indonesia Tbk",
  "UNTD": "PT United Tractors Tbk",
  "UNTR": "PT United Tractors Tbk",
  "UNVR": "PT Unilever Indonesia Tbk",
  "VICI": "PT Victoria Care Indonesia Tbk",
  "VISI": "PT Visi Media Asia Tbk",
  "WEGE": "PT Wijaya Karya Bangunan Gedung Tbk",
  "WEHA": "PT Weha Transportasi Indonesia Tbk",
  "WGSH": "PT Wira Global Solusi Tbk",
  "WIFI": "PT Solusi Sinergi Digital Tbk",
  "WIIM": "PT Wismilak Inti Makmur Tbk",
  "WINE": "PT Hatten Bali Tbk",
  "WINS": "PT Wintermar Offshore Marine Tbk",
  "WOMF": "PT Wahana Ottomitra Multiartha Tbk",
  "WTON": "PT Wijaya Karya Beton Tbk",
  "XCID": "PT XCID Indonesia Tbk",
  "XCIS": "PT XCIS Indonesia Tbk",
  "XCLQ": "PT XCLQ Indonesia Tbk",
  "XSPI": "PT XSPI Indonesia Tbk",
  "YULE": "PT Yulie Sekuritas Indonesia Tbk",
  "YUPI": "PT Yupi Indo Jelly Gum Tbk",
  "ZATA": "PT Bersama Zatta Jaya Tbk",
  "ZYRX": "PT Zyrexindo Mandiri Buana Tbk"
}